Workbook

Sheet Registro de Pruebas
A1: 📊 SISTEMA TRADING EUR/USD — REGISTRO DE PRUEBAS
A2: Capital inicial: $150 USD | Riesgo: 1% | R:R mínimo 1:2 | Actualizado: 2026-03-18
A3: ID | B3: Fecha | C3: Versión | D3: Estrategia | E3: EMA Fast/Slow | F3: ADX Mín | G3: Sesión | H3: Trades | I3: Win Rate % | J3: Sharpe Ratio | K3: Max DD % | L3: Profit Factor | M3: Capital Final $ | N3: P&L Neto $ | O3: Expectancy $/trade | P3: Trades /mes | Q3: Veredicto | R3: Notas
A4: 1 | B4: 2026-03-01 | C4: v1.0 | D4: EMA Backtest Sintético | E4: 20/50 | F4: 0 | G4: Sin filtro | H4: 43 | I4: 0.2093 | J4: -4.88 | K4: 0.1422 | L4: 0.526 | M4: 127.81 | N4: -22.19 | O4: -0.516 | P4: 2.9 | Q4: ❌ No rentable | R4: Datos sintéticos, parámetros defecto
A5: 2 | B5: 2026-03-01 | C5: v1.0 | D5: EMA Backtest Optimizado | E5: 10/30 | F5: 0 | G5: Sin filtro | H5: 59 | I5: 0.3729 | J5: 1.196 | K5: 0.0778 | L5: 1.173 | M5: 159.88 | N5: 9.88 | O5: 0.167 | P5: 4 | Q5: ✅ Sharpe 1.2 | R5: Mejor combo post-optimización
A6: 3 | B6: 2026-03-02 | C6: v1.1 | D6: H4 Solo (datos MT5 reales) | E6: 10/30 | F6: 0 | G6: Sin filtro | H6: 53 | I6: 0.3585 | J6: 0.75 | K6: 0.1238 | L6: 1.105 | M6: 155.27 | N6: 5.27 | O6: 0.099 | P6: 3.5 | Q6: ⚠️ Débil | R6: Primeros datos reales MT5 — 2000 barras
A7: 4 | B7: 2026-03-02 | C7: v1.2 | D7: H4 + Sesión London_NY | E7: 10/30 | F7: 0 | G7: London_NY | H7: 45 | I7: 0.3778 | J7: 1.36 | K7: 0.077 | L7: 1.2 | M7: 158.52 | N7: 8.52 | O7: 0.189 | P7: 3 | Q7: ✅ Bueno | R7: Filtro sesión mejora Sharpe
A8: 5 | B8: 2026-03-03 | C8: v2.0 | D8: H4 + Sesión + M15 Conf. | E8: 10/30 | F8: 0 | G8: London_NY | H8: 4 | I8: 0.5 | J8: 5.19 | K8: 0.02 | L8: 1.97 | M8: 152.95 | N8: 2.95 | O8: 0.739 | P8: 0.3 | Q8: ⚠️ Pocos trades | R8: Solo 4 trades — sin validez estadística
A9: 6 | B9: 2026-03-05 | C9: v2.1 | D9: Cruce EMA + ADX20 + Strict | E9: 10/30 | F9: 20 | G9: London_NY | H9: 30 | I9: 0.4 | J9: 2.07 | K9: 0.0501 | L9: 1.317 | M9: 158.75 | N9: 8.75 | O9: 0.292 | P9: 2 | Q9: ✅ Bueno | R9: ADX bajado a 20, trailing stop activo
A10: 7 | B10: 2026-03-07 | C10: v3.0 | D10: Cruce + Pullback (ambos) | E10: 10/30 | F10: 20 | G10: London_NY | H10: 26 | I10: 0.6154 | J10: 1.57 | K10: 0.044 | L10: 1.62 | M10: 153.43 | N10: 3.43 | O10: 0.132 | P10: 1.7 | Q10: ⚠️ Mixto | R10: Pullback agrega trades pero baja Sharpe
A11: 8 | B11: 2026-03-10 | C11: v4.0 | D11: 7 Indicadores — Momentum | E11: 10/30 | F11: 20 | G11: London_NY | H11: 52 | I11: 0.5385 | J11: -1.68 | K11: 0.076 | L11: 0.91 | M11: 143.08 | N11: -6.92 | O11: -0.133 | P11: 3.5 | Q11: ❌ Negativo | R11: Datos sintéticos — necesita datos MT5 reales
A12: 9 | B12: 2026-03-18 | C12: v4 | D12: 1. Reversión (BB+RSI+Stoch) | E12: 10/30 | F12: 20 | G12: london_ny | H12: 6 | I12: 0.5 | J12: -4.4 | K12: 0.0297 | L12: 0.566 | M12: 148.03 | N12: -1.9668 | O12: -0.3278 | P12: 0.1 | Q12: ⚠️ Pocos trades | R12: Run automático 00:15
A13: 10 | B13: 2026-03-18 | C13: v4 | D13: 2. Cruce EMA (EMA+MACD+ADX) | E13: 10/30 | F13: 20 | G13: london_ny | H13: 14 | I13: 0.5 | J13: -1.858 | K13: 0.0436 | L13: 0.785 | M13: 147.77 | N13: -2.2336 | O13: -0.1596 | P13: 0.3 | Q13: ❌ Negativo | R13: Run automático 00:15
A14: 11 | B14: 2026-03-18 | C14: v4 | D14: 4. Momentum (RSI+MACD+SMA200) | E14: 10/30 | F14: 20 | G14: london_ny | H14: 52 | I14: 0.5385 | J14: -1.683 | K14: 0.0761 | L14: 0.803 | M14: 143.08 | N14: -6.9164 | O14: -0.133 | P14: 1.2 | Q14: ❌ Negativo | R14: Run automático 00:15
A15: 12 | B15: 2026-03-18 | C15: v4 | D15: 5. Pullback EMA | E15: 10/30 | F15: 20 | G15: london_ny | H15: 13 | I15: 0.4615 | J15: -4.648 | K15: 0.0371 | L15: 0.551 | M15: 145.33 | N15: -4.6689 | O15: -0.3591 | P15: 0.3 | Q15: ❌ Negativo | R15: Run automático 00:15
... A17: 14 | B17: 2026-03-18 | C17: v4.2 | D17: 1. Reversion BB+RSI+Stoch | E17: 10/50 | F17: 15 | G17: london_ny | H17: 13 | I17: 0.2308 | J17: -9.57 | K17: 0.101 | L17: 0.35 | M17: 135.21 | N17: -14.79 | O17: -1.138 | P17: 0.3 | Q17: NEGATIVO | R17: Datos MT5 8000 barras reales
A18: 15 | D18: 2. Cruce EMA+MACD+ADX | E18: 10/50 | F18: 15 | G18: london_ny | H18: 4 | I18: 0.25 | J18: -12.25 | K18: 0.044 | L18: 0 | M18: 144.93 | N18: -5.07 | O18: -1.268 | P18: 0.1 | Q18: Pocos trades | R18: Solo 4 trades sin validez estadistica
A19: 16 | B19: 2026-03-18 | C19: v4.2 | D19: 3. Breakout BB+S/R | E19: 10/50 | F19: 15 | G19: london_ny | H19: 11 | I19: 0.1818 | J19: -8.32 | K19: 0.084 | L19: 0.35 | M19: 137.46 | N19: -12.54 | O19: -1.14 | P19: 0.3 | Q19: NEGATIVO | R19: WR 18% muy bajo | T19: RESUMEN AUTOMÁTICO
A20: 17 | B20: 2026-03-18 | C20: v4.2 | D20: 4. Momentum RSI+MACD+SMA200 MEJOR | E20: 10/50 | F20: 15 | G20: london_ny | H20: 26 | I20: 0.5 | J20: 2.11 | K20: 0.031 | L20: 1.52 | M20: 159.68 | N20: 9.68 | O20: 0.373 | P20: 0.6 | Q20: BUENO | R20: MEJOR del run — Sharpe 2.11 con datos reales 5 anos | T20: Total pruebas | U20: =COUNTA(A4:A22)
A21: 18 | B21: 2026-03-18 | C21: v4.2 | D21: 5. Pullback Retroceso EMA | E21: 10/50 | F21: 15 | G21: london_ny | H21: 4 | I21: 0.75 | J21: 11.51 | K21: 0.015 | L21: 3.92 | M21: 156.82 | N21: 6.82 | O21: 1.705 | P21: 0.1 | Q21: Pocos trades | R21: 4 trades — Sharpe no estadistico | T21: Pruebas rentables | U21: =COUNTIF(Q4:Q22,"✅*")
A22: 19 | B22: 2026-03-18 | C22: v4.2 | D22: 6. TODAS combinadas | E22: 10/50 | F22: 15 | G22: london_ny | H22: 26 | I22: 0.5 | J22: 2.11 | K22: 0.031 | L22: 1.52 | M22: 159.68 | N22: 9.68 | O22: 0.373 | P22: 0.6 | Q22: BUENO | R22: MC Ruina 19.5% FIX atr_tp1_mult a 2.0 | T22: Mejor Sharpe | U22: =MAX(J4:J22)
A23: 20 | B23: 2026-03-18 | C23: v4.2 | D23: 1. Reversion (BB+RSI+Stoch) | E23: 10/50 | F23: 12 | G23: london_ny | H23: 13 | I23: 0.2308 | J23: -9.566 | K23: 0.0683 | L23: 0.318 | M23: 140.02 | N23: -9.9796 | O23: -0.7677 | P23: 0.3 | Q23: NEGATIVO | R23: Auto 01:15 | T23: Mejor Win Rate | U23: =MAX(I4:I22)
A24: 28 | B24: 2026-03-18 | C24: v4.2 | D24: 2. Cruce EMA (EMA+MACD+ADX) | E24: 10/50 | F24: 12 | G24: london_ny | H24: 4 | I24: 0.25 | J24: -12.165 | K24: 0.0297 | L24: 0.24 | M24: 146.61 | N24: -3.3878 | O24: -0.847 | P24: 0.1 | Q24: Pocos trades (<10) | R24: Auto 01:15 | T24: Mejor Capital | U24: =MAX(M4:M22)
A25: 29 | B25: 2026-03-18 | C25: v4.2 | D25: 3. Breakout (BB+S/R) | E25: 10/50 | F25: 12 | G25: london_ny | H25: 11 | I25: 0.1818 | J25: -8.239 | K25: 0.0562 | L25: 0.359 | M25: 141.57 | N25: -8.4275 | O25: -0.7661 | P25: 0.2 | Q25: NEGATIVO | R25: Auto 01:15 | T25: Mayor P&L | U25: =MAX(N4:N22)
A26: 30 | B26: 2026-03-18 | C26: v4.2 | D26: 4. Momentum (RSI+MACD+SMA200) | E26: 10/50 | F26: 12 | G26: london_ny | H26: 26 | I26: 0.5 | J26: 2.157 | K26: 0.0204 | L26: 1.328 | M26: 156.53 | N26: 6.5345 | O26: 0.2513 | P26: 0.6 | Q26: BUENO | R26: Auto 01:15
A27: 31 | B27: 2026-03-18 | C27: v4.2 | D27: 5. Pullback (Retroceso EMA) | E27: 10/50 | F27: 12 | G27: london_ny | H27: 4 | I27: 0.75 | J27: 11.575 | K27: 0.01 | L27: 3.95 | M27: 154.53 | N27: 4.5344 | O27: 1.1336 | P27: 0.1 | Q27: Pocos trades (<10) | R27: Auto 01:15
A28: 32 | B28: 2026-03-18 | C28: v4.2 | D28: 6. TODAS (combinadas) | E28: 10/50 | F28: 12 | G28: london_ny | H28: 26 | I28: 0.5 | J28: 2.157 | K28: 0.0204 | L28: 1.328 | M28: 156.53 | N28: 6.5345 | O28: 0.2513 | P28: 0.6 | Q28: BUENO | R28: Auto 01:15
A29: 26 | B29: 2026-03-18 | C29: v4.2 | D29: 1. Reversion (BB+RSI+Stoch) | E29: 10/50 | F29: 12 | G29: london_ny | H29: 13 | I29: 0.2308 | J29: -9.568 | K29: 0.1011 | L29: 0.318 | M29: 135.2 | N29: -14.7971 | O29: -1.1373 | P29: 0.3 | Q29: NEGATIVO | R29: Auto 01:21
A30: 27 | B30: 2026-03-18 | C30: v4.2 | D30: 2. Cruce EMA (EMA+MACD+ADX) | E30: 10/50 | F30: 12 | G30: london_ny | H30: 4 | I30: 0.25 | J30: -12.255 | K30: 0.0443 | L30: 0.237 | M30: 144.92 | N30: -5.0757 | O30: -1.2681 | P30: 0.1 | Q30: Pocos trades (<10) | R30: Auto 01:21
A31: 28 | B31: 2026-03-18 | C31: v4.2 | D31: 3. Breakout (BB+S/R) | E31: 10/50 | F31: 12 | G31: london_ny | H31: 11 | I31: 0.1818 | J31: -8.319 | K31: 0.0836 | L31: 0.356 | M31: 137.46 | N31: -12.5447 | O31: -1.1396 | P31: 0.2 | Q31: NEGATIVO | R31: Auto 01:21
A32: 29 | B32: 2026-03-18 | C32: v4.2 | D32: 4. Momentum (RSI+MACD+SMA200) | E32: 10/50 | F32: 12 | G32: london_ny | H32: 26 | I32: 0.5 | J32: 2.113 | K32: 0.0306 | L32: 1.32 | M32: 159.66 | N32: 9.6551 | O32: 0.3721 | P32: 0.6 | Q32: BUENO | R32: Auto 01:21
A33: 30 | B33: 2026-03-18 | C33: v4.2 | D33: 5. Pullback (Retroceso EMA) | E33: 10/50 | F33: 12 | G33: london_ny | H33: 4 | I33: 0.75 | J33: 11.505 | K33: 0.015 | L33: 3.92 | M33: 156.81 | N33: 6.8122 | O33: 1.7039 | P33: 0.1 | Q33: Pocos trades (<10) | R33: Auto 01:21
A34: 31 | B34: 2026-03-18 | C34: v4.2 | D34: 6. TODAS (combinadas) | E34: 10/50 | F34: 12 | G34: london_ny | H34: 26 | I34: 0.5 | J34: 2.113 | K34: 0.0306 | L34: 1.32 | M34: 159.66 | N34: 9.6551 | O34: 0.3721 | P34: 0.6 | Q34: BUENO | R34: Auto 01:21
A35: 32 | B35: 2026-03-18 | C35: v5.3 | D35: 1. Reversion (BB+RSI+Stoch) | E35: 10/50 | F35: 12 | G35: london_ny | H35: 13 | I35: 0.2308 | J35: -11.517 | K35: 0.1066 | L35: 0.258 | M35: 134 | N35: -15.9959 | O35: -1.2296 | P35: 0.3 | Q35: NEGATIVO | R35: Auto v5.3 17:53
A36: 33 | B36: 2026-03-18 | C36: v5.3 | D36: 2. Cruce EMA (EMA+MACD+ADX) | E36: 10/50 | F36: 12 | G36: london_ny | H36: 4 | I36: 0.25 | J36: -12.255 | K36: 0.0443 | L36: 0.237 | M36: 144.92 | N36: -5.0757 | O36: -1.2681 | P36: 0.1 | Q36: Pocos trades (<10) | R36: Auto v5.3 17:53
A37: 34 | B37: 2026-03-18 | C37: v5.3 | D37: 3. Breakout (BB+S/R) | E37: 10/50 | F37: 12 | G37: london_ny | H37: 11 | I37: 0.1818 | J37: -9.819 | K37: 0.0899 | L37: 0.306 | M37: 136.52 | N37: -13.4822 | O37: -1.2249 | P37: 0.2 | Q37: NEGATIVO | R37: Auto v5.3 17:53
... A98: 95 | B98: 2026-04-14 | C98: v5.4 | D98: 4. TODAS (combinadas) | E98: 10/55 | F98: 15 | G98: london_ny | H98: 579 | I98: 0.4076 | J98: -0.318 | K98: 0.5705 | L98: 0.903 | M98: 98.85 | N98: -51.1491 | O98: -0.0878 | P98: 13 | Q98: NEGATIVO | R98: Auto v5.3 22:53

Sheet Dashboard
A1: 📈 DASHBOARD DE MÉTRICAS — Evolución del Sistema
A3: Métrica | B3: Mejor | C3: Última | D3: Objetivo | E3: Estado
A4: Win Rate | B4: =MAX('Registro de Pruebas'!I4:I100) | C4: ='Registro de Pruebas'!I11 | D4: 55% | E4: =IF(C4>=0.55,"✅ OK","⚠️ Mejorar")
A5: Sharpe Ratio | B5: =MAX('Registro de Pruebas'!J4:J100) | C5: ='Registro de Pruebas'!J11 | D5: >1.0 | E5: =IF(C5>=1,"✅ OK","⚠️ Mejorar")
A6: Max Drawdown | B6: =MIN('Registro de Pruebas'!K4:K100) | C6: ='Registro de Pruebas'!K11 | D6: <10% | E6: =IF(C6<=0.1,"✅ OK","⚠️ Alto")
A7: Profit Factor | B7: =MAX('Registro de Pruebas'!L4:L100) | C7: ='Registro de Pruebas'!L11 | D7: >1.5 | E7: =IF(C7>=1.5,"✅ OK","⚠️ Mejorar")
A8: P&L Neto $ | B8: =MAX('Registro de Pruebas'!N4:N100) | C8: ='Registro de Pruebas'!N11 | D8: >$0 | E8: =IF(C8>0,"✅ OK","❌ Negativo")
A9: Trades/mes | B9: =MAX('Registro de Pruebas'!P4:P100) | C9: ='Registro de Pruebas'!P11 | D9: 6-8 | E9: =IF(AND(C9>=6,C9<=8),"✅ OK","⚠️ Ajustar")
A10: Capital Final | B10: =MAX('Registro de Pruebas'!M4:M100) | C10: ='Registro de Pruebas'!M11 | D10: >$160 | E10: =IF(C10>160,"✅ OK","⚠️ Mejorar")
A13: EVOLUCIÓN POR VERSIÓN
A14: Versión | B14: Estrategia | C14: Trades | D14: Win Rate | E14: Sharpe | F14: P&L $ | G14: Estado
A15: v1.0 | B15: EMA Base (sintético) | C15: 43 | D15: 20.9% | E15: -4.88 | F15: -22.19 | G15: ❌
A16: v1.1 | B16: H4 Solo (MT5 real) | C16: 53 | D16: 35.9% | E16: 0.75 | F16: 5.27 | G16: ⚠️
A17: v1.2 | B17: H4 + Sesión London_NY | C17: 45 | D17: 37.8% | E17: 1.36 | F17: 8.52 | G17: ✅
A18: v2.0 | B18: H4 + M15 (4 trades) | C18: 4 | D18: 50.0% | E18: 5.19 | F18: 2.95 | G18: ⚠️
A19: v2.1 | B19: ADX20 + Trailing | C19: 30 | D19: 40.0% | E19: 2.07 | F19: 8.75 | G19: ✅
A20: v3.0 | B20: Cruce + Pullback | C20: 26 | D20: 61.5% | E20: 1.57 | F20: 3.43 | G20: ⚠️
A21: v4.0 | B21: 7 Indicadores (en progreso) | C21: 52 | D21: 53.9% | E21: -1.68 | F21: -6.92 | G21: ❌

Sheet Configuración
A1: ⚙️ PARÁMETROS DEL SISTEMA — config.py
A3: CAPITAL Y RIESGO
A4: Parámetro | B4: Valor | C4: Unidad | D4: Descripción
A5: Capital Inicial | B5: $150.00 | C5: USD | D5: No modificar hasta sistema rentable 3 meses
A6: Riesgo por Trade | B6: 1% | C6: Del capital | D6: NO subir hasta Win Rate > 55% consistente
A7: R:R Mínimo | B7: 1:2 | D7: Take Profit = 2× Stop Loss mínimo
A8: Drawdown Máximo | B8: 15% | D8: Parar sistema si se supera
A9: Umbral de Ruina | B9: 30% | D9: Parar y revisar si capital baja a $105
A10: Max Trades/Día | B10: 4 | D10: Incluye cruce + pullback
A12: INDICADORES (7 de la guía)
A13: Parámetro | B13: Valor | C13: Unidad | D13: Descripción
A14: EMA Rápida | B14: 10 | C14: Períodos | D14: Tendencia de corto plazo
A15: EMA Lenta | B15: 30 | C15: Períodos | D15: Tendencia de medio plazo
A16: SMA Macro | B16: 200 | C16: Períodos | D16: Filtro: solo long sobre SMA200
A17: RSI | B17: 14 | C17: Períodos | D17: CORRECCIÓN: RSI alto = momentum, no bloqueo
A18: Estocástico | B18: 5/3/3 | C18: K/D/Smooth | D18: Sobreventa < 25 | Sobrecompra > 75
A19: MACD | B19: 12/26/9 | C19: Fast/Slow/Signal | D19: Cruce = entrada | Histograma = fuerza
A20: Bollinger Bands | B20: 20/2 | C20: Período/StdDev | D20: Squeeze = movimiento inminente
A21: ADX Mínimo | B21: 20 | D21: < 20 = rango, evitar | > 25 = tendencia fuerte
A23: GESTIÓN DE SALIDAS
A24: Parámetro | B24: Valor | C24: Unidad | D24: Descripción
A25: Stop Loss | B25: ATR × 1.5 | D25: Dinámico basado en volatilidad real
A26: Take Profit 1 (50%) | B26: ATR × 1.5 | D26: Cierra mitad de posición — asegura ganancia
A27: Take Profit 2 (50%) | B27: ATR × 3.0 | D27: Deja correr la otra mitad
A28: Trailing Stop | B28: ATR × 1.0 | D28: Activo después de TP1 — protege ganancias
A30: SESIÓN Y TIMEFRAMES
A31: Parámetro | B31: Valor | C31: Unidad | D31: Descripción
A32: Timeframe principal | B32: H4 | D32: Dirección macro de la tendencia
A33: Timeframe confirmación | B33: M15 | D33: Alineamiento antes de entrar
A34: Sesión activa | B34: London+NY | C34: 08-21 UTC | D34: Mayor liquidez y tendencias claras
A35: Evitar | B35: Sesión Asia | C35: 00-07 UTC | D35: Baja liquidez, señales falsas
A36: Evitar noticias | B36: FOMC, NFP, CPI | D36: Salir antes o esperar post-noticia

Sheet Trades Reales
A1: 📋 REGISTRO DE TRADES REALES — Llenar después de cada operación
A2: ⚠️ Este registro es para PAPER TRADING o trades reales — NO para backtest
A3: # | B3: Fecha Entrada | C3: Hora Entrada | D3: Par | E3: Dirección | F3: Precio Entrada | G3: Stop Loss | H3: Take Profit | I3: Precio Salida | J3: Fecha Salida | K3: P&L USD | L3: Resultado | M3: Estrategia Usada | N3: Notas / Lección
A55: Total trades | B55: =COUNTA(A4:A53)
A56: Wins | B56: =COUNTIF(L4:L53,"WIN")
A57: Losses | B57: =COUNTIF(L4:L53,"LOSS")
A58: Win Rate | B58: =IF(B56>0,B57/B56,0)
A59: P&L Total | B59: =SUM(K4:K53)
A60: Mejor trade | B60: =MAX(K4:K53)
A61: Peor trade | B61: =MIN(K4:K53)
A62: Avg P&L | B62: =AVERAGE(K4:K53)

Sheet Mi Análisis
A1: 🧠 MI ANÁLISIS — Qué funcionó y qué mejorar
A3: DIAGNÓSTICO ACTUAL
A4: Problema principal | C4: Solo 2-3 trades/mes con datos reales MT5 → Sin suficientes datos estadísticos
A5: Win Rate actual | C5: 38-40% con configuración básica → Necesita pullback + SMA200 para llegar a 55%
A6: Sharpe real | C6: 0.75 a 1.36 según configuración → Meta: > 2.0 con datos 8000 barras
A7: Problema datos | C7: Solo 2000 barras H4 (~15 meses) → URGENTE: descargar 8000 barras (~5 años)
A9: CORRECCIONES APLICADAS
A10: RSI corregido | C10: RSI alto = momentum fuerte (guía) → Ya NO bloqueamos señales con RSI > 65
A11: ADX bajado 25→20 | C11: Más trades sin perder calidad → De 2 a ~4 trades/mes esperados
A12: SMA 200 agregado | C12: Filtro macro: solo long si precio > SMA200 → Elimina trades contra tendencia mayor
A13: 7 indicadores activos | C13: Stoch + MACD + BB + ADX + EMA + RSI + S/R → Confirmación múltiple
A15: PRÓXIMOS PASOS
A16: Paso 1 (HOY) | C16: python run.py --download → Descargar 8000 barras H4 de MT5
A17: Paso 2 (esta semana) | C17: python run.py --all → Ver resultados con datos reales 5 años
A18: Paso 3 | C18: Ajustar estrategia según Walk-Forward → Usar EMA recomendada por el WF
A19: Paso 4 (si Sharpe > 1.5) | C19: Paper trading 3 meses mínimo → Validar en tiempo real sin dinero
A20: Paso 5 (si Paper OK) | C20: Live trading $150 real → Solo después de 3 meses paper trading positivo
